mli/__init__.py
mli/client.py
mli/fake_proc.py
mli/formatter.py
mli/langchain_client.py
mli/params.py
mli/server.py
mlipy-0.1.57.dist-info/LICENSE
mlipy-0.1.57.dist-info/METADATA
mlipy-0.1.57.dist-info/WHEEL
mlipy-0.1.57.dist-info/RECORD
