Metadata-Version: 2.1
Name: mlipy
Version: 0.1.57
Summary: Python-based Machine Learning Interface
Home-page: https://github.com/tangledgroup/mlipy
License: MIT
Author: Marko Tasic
Author-email: mtasic85@gmail.com
Requires-Python: >=3.11,<4.0
Classifier: License :: OSI Approved :: MIT License
Classifier: Programming Language :: Python :: 3
Classifier: Programming Language :: Python :: 3.11
Classifier: Programming Language :: Python :: 3.12
Provides-Extra: langchain
Provides-Extra: uvloop
Requires-Dist: aiohttp[speedups] (>=3.9.5,<4.0.0)
Requires-Dist: huggingface-hub (>=0.24.1,<0.25.0)
Requires-Dist: jinja2 (>=3.1.4,<4.0.0)
Requires-Dist: langchain (>=0.2.11,<0.3.0) ; extra == "langchain"
Requires-Dist: protobuf (>=5.27.2,<6.0.0)
Requires-Dist: sentencepiece (>=0.2.0,<0.3.0)
Requires-Dist: tiktoken (>=0.7.0,<0.8.0)
Requires-Dist: transformers (>=4.43.1,<5.0.0)
Requires-Dist: uvloop (>=0.19.0,<0.20.0) ; extra == "uvloop"
Project-URL: Repository, https://github.com/tangledgroup/mlipy
